arikaim/core/api_descriptor.py
arikaim/core/arikaim.py
arikaim/core/container.py
arikaim/core/controller.py
arikaim/core/errors.py
arikaim/core/globals.py
arikaim/core/logger.py
arikaim/core/packages.py
arikaim/core/path.py
arikaim/core/response.py
arikaim/core/server.py
arikaim/core/service.py
arikaim/core/utils.py
arikaim/core/access/access.py
arikaim/core/access/auth_error.py
arikaim/core/access/middleware/multiple.py
arikaim/core/access/providers/php_session.py
arikaim/core/access/providers/token.py
arikaim/core/admin/admin.py
arikaim/core/admin/controllers/info.py
arikaim/core/admin/controllers/service.py
arikaim/core/admin/controllers/service_route.py
arikaim/core/admin/controllers/service_routes.py
arikaim/core/admin/controllers/services_list.py
arikaim/core/collection/property.py
arikaim/core/console/app.py
arikaim/core/console/config.py
arikaim/core/console/packages.py
arikaim/core/console/templates/config_file.py
arikaim/core/db/db.py
arikaim/core/db/models/access_tokens.py
arikaim/core/db/models/jobs.py
arikaim/core/db/models/permission_relations.py
arikaim/core/db/models/permissions.py
arikaim/core/db/models/users.py
arikaim/core/queue/job.py
arikaim/core/queue/queue.py
arikaim_service_server-0.5.3.data/scripts/arikaim-server
arikaim_service_server-0.5.3.dist-info/METADATA
arikaim_service_server-0.5.3.dist-info/WHEEL
arikaim_service_server-0.5.3.dist-info/top_level.txt
arikaim_service_server-0.5.3.dist-info/RECORD
