Metadata-Version: 2.1
Name: arikaim-service-server
Version: 0.5.3
Summary: Arikaim python service server
Home-page: 
Download-URL: 
Author: Intersoft Ltd
Author-email: info@arikaim.com
License: MIT License
Keywords: arikaim
Requires-Dist: uvicorn
Requires-Dist: starlette
Requires-Dist: pymysql
Requires-Dist: peewee
Requires-Dist: click
Requires-Dist: rq
Requires-Dist: rq-scheduler
Requires-Dist: rich
Requires-Dist: requests
Requires-Dist: pydantic
Requires-Dist: python-multipart
Requires-Dist: pymitter
